conda_pip_minimal/__about__.py
conda_pip_minimal/__init__.py
conda_pip_minimal/__main__.py
conda_pip_minimal/cli.py
conda_pip_minimal/cmd.py
conda_pip_minimal/conda_env.py
conda_pip_minimal/deps.py
conda_pip_minimal/export.py
conda_pip_minimal/logging.py
conda_pip_minimal/min.py
conda_pip_minimal/result_capture.py
conda_pip_minimal/version.py
conda_pip_minimal-0.2.1.dist-info/METADATA
conda_pip_minimal-0.2.1.dist-info/WHEEL
conda_pip_minimal-0.2.1.dist-info/entry_points.txt
conda_pip_minimal-0.2.1.dist-info/RECORD
