Metadata-Version: 2.1
Name: conda-pip-minimal
Version: 0.2.1
Summary: Conda+Pip minimal env exports
Project-URL: Homepage, https://github.com/indigoviolet/conda-pip-minimal
Author-email: Venky Iyer <indigoviolet@gmail.com>
License-Expression: MIT
Keywords: conda,environment.yaml,packaging,pip
Classifier: Intended Audience :: Developers
Classifier: Intended Audience :: Science/Research
Classifier: Topic :: Software Development :: Build Tools
Requires-Python: >=3.8
Requires-Dist: importlib-metadata~=5.0.0
Requires-Dist: loguru
Requires-Dist: more-itertools
Requires-Dist: ruamel-yaml~=0.17.21
Requires-Dist: semver>=3.0.0
Requires-Dist: trio~=0.22.0
Requires-Dist: typer~=0.6.1
